LICENSE
MANIFEST.in
README.md
setup.cfg
setup.py
structure_threader/__init__.py
structure_threader/argparser.py
structure_threader/structure_threader.py
structure_threader.egg-info/PKG-INFO
structure_threader.egg-info/SOURCES.txt
structure_threader.egg-info/dependency_links.txt
structure_threader.egg-info/entry_points.txt
structure_threader.egg-info/requires.txt
structure_threader.egg-info/top_level.txt
structure_threader/bins/__init__.py
structure_threader/bins/linux/MavericK
structure_threader/bins/linux/__init__.py
structure_threader/bins/linux/fastStructure
structure_threader/bins/linux/structure
structure_threader/bins/osx/MavericK
structure_threader/bins/osx/fastStructure
structure_threader/bins/osx/structure
structure_threader/colorer/__init__.py
structure_threader/colorer/colorer.py
structure_threader/evanno/__init__.py
structure_threader/evanno/fastChooseK.py
structure_threader/evanno/harvesterCore.py
structure_threader/evanno/structureHarvester.py
structure_threader/plotter/__init__.py
structure_threader/plotter/html_template.py
structure_threader/plotter/structplot.py
structure_threader/sanity_checks/__init__.py
structure_threader/sanity_checks/sanity.py
structure_threader/skeletons/__init__.py
structure_threader/skeletons/stparams.py
structure_threader/wrappers/__init__.py
structure_threader/wrappers/alstructure_wrapper.R
structure_threader/wrappers/alstructure_wrapper.py
structure_threader/wrappers/faststructure_wrapper.py
structure_threader/wrappers/maverick_wrapper.py
structure_threader/wrappers/structure_wrapper.py