Metadata-Version: 2.1
Name: structure_threader
Version: 1.3.11
Summary: A program to parallelize runs of 'Structure', 'fastStructure' and 'MavericK'.
Home-page: https://gitlab.com/StuntsPT/Structure_threader
Download-URL: https://gitlab.com/StuntsPT/Structure_threader/-/archive/1.3.11/Structure_threader-1.3.11.tar.gz
Author: Francisco Pina-Martins
Author-email: f.pinamartins@gmail.com
License: GPL3
Classifier: Intended Audience :: Science/Research
Classifier: License :: OSI Approved :: GNU General Public License v3 (GPLv3)
Classifier: Natural Language :: English
Classifier: Operating System :: POSIX :: Linux
Classifier: Topic :: Scientific/Engineering :: Bio-Informatics
Classifier: Programming Language :: Python :: 3 :: Only
Classifier: Programming Language :: Python :: 3.4
Classifier: Programming Language :: Python :: 3.5
Classifier: Programming Language :: Python :: 3.6
Classifier: Programming Language :: Python :: 3.7
License-File: LICENSE
Requires-Dist: plotly>=4.1.1
Requires-Dist: colorlover
Requires-Dist: numpy>=1.12.1
Requires-Dist: matplotlib
